upboard/__init__.py
upboard/upboard_publish.py
upboard/upboard_server.py
upboard/etc/systemd/upboard.service
upboard-0.0.1b4.dist-info/licenses/LICENSE
upboard-0.0.1b4.dist-info/METADATA
upboard-0.0.1b4.dist-info/WHEEL
upboard-0.0.1b4.dist-info/entry_points.txt
upboard-0.0.1b4.dist-info/top_level.txt
upboard-0.0.1b4.dist-info/RECORD
