Metadata-Version: 2.4
Name: upboard
Version: 0.0.1b4
Summary: Update-Board is a lightweight CLI tool for managing and delivering updated versions of applications during testing.
Author-email: Zero Kwok <zero.kwok@foxmail.com>
License: MIT License
Project-URL: Homepage, https://github.com/ZeroKwok/upboard
Project-URL: Issues, https://github.com/ZeroKwok/upboard/issues
Keywords: autoupdate,tools
Classifier: Development Status :: 4 - Beta
Classifier: Intended Audience :: Developers
Classifier: Topic :: Software Development :: Build Tools
Classifier: Programming Language :: Python
Classifier: Programming Language :: Python :: 3 :: Only
Classifier: Programming Language :: Python :: 3
Classifier: Programming Language :: Python :: 3.7
Classifier: Programming Language :: Python :: 3.8
Classifier: Programming Language :: Python :: 3.9
Classifier: Programming Language :: Python :: 3.10
Classifier: Programming Language :: Python :: 3.11
Requires-Python: >=3.7
License-File: LICENSE
Requires-Dist: Flask
Requires-Dist: Flask-Reuploaded
Requires-Dist: waitress
Dynamic: license-file
